{
  "metadata": {
    "lastUpdated": "2026-07-06T11:57:46.938Z",
    "recordCount": 36,
    "version": "1.0"
  },
  "records": [
    {
      "date": "2026-07-02",
      "station": "AKOLA",
      "rainfall_mm": 5.2,
      "rf_since_09hrs": null,
      "source": "imd_scrape",
      "updatedAt": "2026-07-04T10:14:43.670Z"
    },
    {
      "date": "2026-07-02",
      "station": "AMRAVATI",
      "rainfall_mm": 13.4,
      "rf_since_09hrs": null,
      "source": "imd_scrape",
      "updatedAt": "2026-07-04T10:14:43.670Z"
    },
    {
      "date": "2026-07-02",
      "station": "BHANDARA",
      "rainfall_mm": 15,
      "rf_since_09hrs": null,
      "source": "imd_scrape",
      "updatedAt": "2026-07-04T10:14:43.670Z"
    },
    {
      "date": "2026-07-02",
      "station": "BULDANA",
      "rainfall_mm": 7,
      "rf_since_09hrs": null,
      "source": "imd_scrape",
      "updatedAt": "2026-07-04T10:14:43.670Z"
    },
    {
      "date": "2026-07-02",
      "station": "BRAHMPURI",
      "rainfall_mm": 1.8,
      "rf_since_09hrs": null,
      "source": "imd_scrape",
      "updatedAt": "2026-07-04T10:14:43.670Z"
    },
    {
      "date": "2026-07-02",
      "station": "CHANDRAPUR",
      "rainfall_mm": 55,
      "rf_since_09hrs": null,
      "source": "imd_scrape",
      "updatedAt": "2026-07-04T10:14:43.670Z"
    },
    {
      "date": "2026-07-02",
      "station": "GADCHIROLI",
      "rainfall_mm": 5.2,
      "rf_since_09hrs": null,
      "source": "imd_scrape",
      "updatedAt": "2026-07-04T10:14:43.670Z"
    },
    {
      "date": "2026-07-02",
      "station": "GONDIA",
      "rainfall_mm": 174.8,
      "rf_since_09hrs": null,
      "source": "imd_scrape",
      "updatedAt": "2026-07-04T10:14:43.670Z"
    },
    {
      "date": "2026-07-02",
      "station": "NAGPUR",
      "rainfall_mm": 5.1,
      "rf_since_09hrs": null,
      "source": "imd_scrape",
      "updatedAt": "2026-07-04T10:14:43.670Z"
    },
    {
      "date": "2026-07-02",
      "station": "WARDHA",
      "rainfall_mm": 11.4,
      "rf_since_09hrs": null,
      "source": "imd_scrape",
      "updatedAt": "2026-07-04T10:14:43.670Z"
    },
    {
      "date": "2026-07-02",
      "station": "WASHIM",
      "rainfall_mm": 11.8,
      "rf_since_09hrs": null,
      "source": "imd_scrape",
      "updatedAt": "2026-07-04T10:14:43.670Z"
    },
    {
      "date": "2026-07-02",
      "station": "YAVATMAL",
      "rainfall_mm": 60,
      "rf_since_09hrs": null,
      "source": "imd_scrape",
      "updatedAt": "2026-07-04T10:14:43.670Z"
    },
    {
      "date": "2026-07-03",
      "station": "AKOLA",
      "rainfall_mm": 12.4,
      "rf_since_09hrs": null,
      "source": "imd_scrape",
      "updatedAt": "2026-07-05T05:22:20.274Z"
    },
    {
      "date": "2026-07-03",
      "station": "AMRAVATI",
      "rainfall_mm": 1.4,
      "rf_since_09hrs": null,
      "source": "imd_scrape",
      "updatedAt": "2026-07-05T05:22:20.274Z"
    },
    {
      "date": "2026-07-03",
      "station": "BHANDARA",
      "rainfall_mm": 10,
      "rf_since_09hrs": null,
      "source": "imd_scrape",
      "updatedAt": "2026-07-05T05:22:20.274Z"
    },
    {
      "date": "2026-07-03",
      "station": "BULDANA",
      "rainfall_mm": 5,
      "rf_since_09hrs": null,
      "source": "imd_scrape",
      "updatedAt": "2026-07-05T05:22:20.274Z"
    },
    {
      "date": "2026-07-03",
      "station": "BRAHMPURI",
      "rainfall_mm": 11.6,
      "rf_since_09hrs": null,
      "source": "imd_scrape",
      "updatedAt": "2026-07-05T05:22:20.274Z"
    },
    {
      "date": "2026-07-03",
      "station": "CHANDRAPUR",
      "rainfall_mm": 3,
      "rf_since_09hrs": null,
      "source": "imd_scrape",
      "updatedAt": "2026-07-05T05:22:20.274Z"
    },
    {
      "date": "2026-07-03",
      "station": "GADCHIROLI",
      "rainfall_mm": 5,
      "rf_since_09hrs": null,
      "source": "imd_scrape",
      "updatedAt": "2026-07-05T05:22:20.274Z"
    },
    {
      "date": "2026-07-03",
      "station": "GONDIA",
      "rainfall_mm": 11,
      "rf_since_09hrs": null,
      "source": "imd_scrape",
      "updatedAt": "2026-07-05T05:22:20.274Z"
    },
    {
      "date": "2026-07-03",
      "station": "NAGPUR",
      "rainfall_mm": 5,
      "rf_since_09hrs": null,
      "source": "imd_scrape",
      "updatedAt": "2026-07-05T05:22:20.274Z"
    },
    {
      "date": "2026-07-03",
      "station": "WARDHA",
      "rainfall_mm": 0,
      "rf_since_09hrs": null,
      "source": "imd_scrape",
      "updatedAt": "2026-07-05T05:22:20.274Z"
    },
    {
      "date": "2026-07-03",
      "station": "WASHIM",
      "rainfall_mm": 8,
      "rf_since_09hrs": null,
      "source": "imd_scrape",
      "updatedAt": "2026-07-05T05:22:20.274Z"
    },
    {
      "date": "2026-07-03",
      "station": "YAVATMAL",
      "rainfall_mm": 7.4,
      "rf_since_09hrs": null,
      "source": "imd_scrape",
      "updatedAt": "2026-07-05T05:22:20.274Z"
    },
    {
      "date": "2026-07-04",
      "station": "AKOLA",
      "rainfall_mm": 5.4,
      "rf_since_09hrs": 3.3,
      "source": "auto_backfill",
      "updatedAt": "2026-07-05T05:22:08.554Z"
    },
    {
      "date": "2026-07-04",
      "station": "AMRAVATI",
      "rainfall_mm": 5.5,
      "rf_since_09hrs": 1.8,
      "source": "auto_backfill",
      "updatedAt": "2026-07-05T05:22:08.554Z"
    },
    {
      "date": "2026-07-04",
      "station": "BHANDARA",
      "rainfall_mm": 69.9,
      "rf_since_09hrs": 48.6,
      "source": "auto_backfill",
      "updatedAt": "2026-07-05T05:22:08.554Z"
    },
    {
      "date": "2026-07-04",
      "station": "BULDANA",
      "rainfall_mm": 0,
      "rf_since_09hrs": 0,
      "source": "auto_backfill",
      "updatedAt": "2026-07-05T05:22:08.554Z"
    },
    {
      "date": "2026-07-04",
      "station": "BRAHMPURI",
      "rainfall_mm": 10,
      "rf_since_09hrs": 4.6,
      "source": "auto_backfill",
      "updatedAt": "2026-07-05T05:22:08.554Z"
    },
    {
      "date": "2026-07-04",
      "station": "CHANDRAPUR",
      "rainfall_mm": 13.8,
      "rf_since_09hrs": 4.4,
      "source": "auto_backfill",
      "updatedAt": "2026-07-05T05:22:08.554Z"
    },
    {
      "date": "2026-07-04",
      "station": "GADCHIROLI",
      "rainfall_mm": 0,
      "rf_since_09hrs": 0,
      "source": "auto_backfill",
      "updatedAt": "2026-07-05T05:22:08.554Z"
    },
    {
      "date": "2026-07-04",
      "station": "GONDIA",
      "rainfall_mm": 6.7,
      "rf_since_09hrs": 3.3,
      "source": "auto_backfill",
      "updatedAt": "2026-07-05T05:22:08.554Z"
    },
    {
      "date": "2026-07-04",
      "station": "NAGPUR",
      "rainfall_mm": 5.4,
      "rf_since_09hrs": 2.6,
      "source": "auto_backfill",
      "updatedAt": "2026-07-05T05:22:08.554Z"
    },
    {
      "date": "2026-07-04",
      "station": "WARDHA",
      "rainfall_mm": 0,
      "rf_since_09hrs": 0,
      "source": "auto_backfill",
      "updatedAt": "2026-07-05T05:22:08.554Z"
    },
    {
      "date": "2026-07-04",
      "station": "WASHIM",
      "rainfall_mm": 0,
      "rf_since_09hrs": 0,
      "source": "auto_backfill",
      "updatedAt": "2026-07-05T05:22:08.554Z"
    },
    {
      "date": "2026-07-04",
      "station": "YAVATMAL",
      "rainfall_mm": 5,
      "rf_since_09hrs": 1.8,
      "source": "auto_backfill",
      "updatedAt": "2026-07-05T05:22:08.554Z"
    }
  ]
}